rouge4llm/evaluator.py
rouge4llm/summarizer.py
rouge4llm/utils.py
rouge4llm/commands/run.py
rouge4llm-0.1.2.dist-info/METADATA
rouge4llm-0.1.2.dist-info/WHEEL
rouge4llm-0.1.2.dist-info/top_level.txt
rouge4llm-0.1.2.dist-info/RECORD
