Metadata-Version: 2.2
Name: rouge4llm
Version: 0.1.2
Summary: Add your description here
Requires-Python: >=3.11.5
Requires-Dist: nltk>=3.9.1
Requires-Dist: numpy<2.0
Requires-Dist: py-rouge>=1.1
Requires-Dist: rougek>=0.1.5
Requires-Dist: setuptools>=75.8.0
Requires-Dist: torch==2.2.2
Requires-Dist: transformers>=4.48.1
Requires-Dist: accelerate>=1.3.0
Requires-Dist: datasets>=3.2.0
Requires-Dist: sienna>=0.2.6
Requires-Dist: aclsum>=0.1.2
